{"jsonapi":{"version":"1.0"},"data":{"type":"project","id":"ember-navigation-guard","attributes":{"name":"ember-navigation-guard","version":"0.1.0","navigationIndex":[{"type":"components","items":[{"id":"ember-navigation-guard/components/navigation-guard","path":"components/navigation-guard","name":"{{navigation-guard}}"}]},{"type":"services","items":[{"id":"ember-navigation-guard/services/navigation-guard","path":"services/navigation-guard","name":"NavigationGuard"}]}]},"relationships":{"modules":{"data":[{"type":"module","id":"ember-navigation-guard/components/navigation-guard"},{"type":"module","id":"ember-navigation-guard/services/navigation-guard"}]}}},"included":[{"type":"component","id":"ember-navigation-guard/components/navigation-guard~NavigationGuardComponent","attributes":{"name":"NavigationGuardComponent","file":"ember-navigation-guard/components/navigation-guard","exportType":"default","description":null,"lineNumber":6,"access":"public","isInterface":false,"decorators":[],"tags":[],"fields":[],"methods":[],"accessors":[],"parentClassId":"@glimmer/component~Component","arguments":[],"yields":[]},"relationships":{"parentClass":{"data":null}}},{"type":"module","id":"ember-navigation-guard/components/navigation-guard","attributes":{"file":"ember-navigation-guard/components/navigation-guard","functions":[],"variables":[]},"relationships":{"classes":{"data":[]},"components":{"data":[{"type":"component","id":"ember-navigation-guard/components/navigation-guard~NavigationGuardComponent"}]}}},{"type":"class","id":"ember-navigation-guard/services/navigation-guard~NavigationGuardService","attributes":{"name":"NavigationGuardService","file":"ember-navigation-guard/services/navigation-guard","exportType":"default","description":null,"lineNumber":17,"access":"public","isInterface":false,"decorators":[],"tags":[],"fields":[],"methods":[],"accessors":[{"name":"preventNav","description":null,"lineNumber":65,"access":"public","tags":[],"file":"ember-navigation-guard/services/navigation-guard","type":"any","isStatic":false,"decorators":[],"hasGetter":true,"hasSetter":false},{"name":"firstMessage","description":null,"lineNumber":81,"access":"public","tags":[],"file":"ember-navigation-guard/services/navigation-guard","type":"any","isStatic":false,"decorators":[],"hasGetter":true,"hasSetter":false},{"name":"lastMessage","description":null,"lineNumber":85,"access":"public","tags":[],"file":"ember-navigation-guard/services/navigation-guard","type":"any","isStatic":false,"decorators":[],"hasGetter":true,"hasSetter":false}],"parentClassId":"@ember/service~Service"},"relationships":{"parentClass":{"data":null}}},{"type":"module","id":"ember-navigation-guard/services/navigation-guard","attributes":{"file":"ember-navigation-guard/services/navigation-guard","functions":[],"variables":[]},"relationships":{"classes":{"data":[{"type":"class","id":"ember-navigation-guard/services/navigation-guard~NavigationGuardService"}]},"components":{"data":[]}}}]}
